treepoem/__init__.py
treepoem/__main__.py
treepoem/data.py
treepoem/py.typed
treepoem/postscriptbarcode/CHANGES
treepoem/postscriptbarcode/LICENSE
treepoem/postscriptbarcode/README
treepoem/postscriptbarcode/__init__.py
treepoem/postscriptbarcode/barcode.ps
treepoem-3.28.0.dist-info/licenses/LICENSE
treepoem-3.28.0.dist-info/METADATA
treepoem-3.28.0.dist-info/WHEEL
treepoem-3.28.0.dist-info/entry_points.txt
treepoem-3.28.0.dist-info/top_level.txt
treepoem-3.28.0.dist-info/RECORD
