Metadata-Version: 2.4
Name: treepoem
Version: 3.28.0
Summary: Barcode rendering for Python supporting QRcode, Aztec, PDF417, I25, Code128, Code39 and many more types.
Author-email: Christian Muirhead <xtian@babbageclunk.com>
Maintainer-email: Adam Johnson <me@adamj.eu>
License-Expression: MIT
Project-URL: Changelog, https://github.com/adamchainz/treepoem/blob/main/CHANGELOG.rst
Project-URL: Funding, https://adamj.eu/books/
Project-URL: Repository, https://github.com/adamchainz/treepoem
Keywords: barcode bwipp postscript ghostscript qr qrcode aztec azteccode pdf417 interleaved2of5 i25 code128 code39
Classifier: Development Status :: 3 - Alpha
Classifier: Intended Audience :: Developers
Classifier: Natural Language :: English
Classifier: Programming Language :: Python :: 3 :: Only
Classifier: Programming Language :: Python :: 3.9
Classifier: Programming Language :: Python :: 3.10
Classifier: Programming Language :: Python :: 3.11
Classifier: Programming Language :: Python :: 3.12
Classifier: Programming Language :: Python :: 3.13
Classifier: Programming Language :: Python :: 3.14
Classifier: Typing :: Typed
Requires-Python: >=3.9
License-File: LICENSE
Requires-Dist: pillow
Dynamic: license-file
